<?xml version="1.0" encoding="UTF-8"?>
<objects serializationModel="Studio.02.02.00">
	<object class="AudioFile" id="{60a330b0-dc77-48c8-ac4e-ba8415f29981}">
		<property name="assetPath">
			<value>onlymp3.to_-_Palace_of_Twilight_The_Legend_of_Zelda_Twilight_Princess-AjT8lSPQY6I-192k-1707279383.mp3</value>
		</property>
		<property name="isStreaming">
			<value>true</value>
		</property>
		<property name="frequencyInKHz">
			<value>48</value>
		</property>
		<property name="channelCount">
			<value>2</value>
		</property>
		<property name="length">
			<value>215.304</value>
		</property>
		<relationship name="masterAssetFolder">
			<destination>{094ab35d-17fa-4645-b4da-0ad9f83c9a79}</destination>
		</relationship>
	</object>
</objects>
