<?xml version="1.0" encoding="UTF-8"?>
<objects serializationModel="Studio.02.02.00">
	<object class="ParameterPreset" id="{94f8d449-4780-4bdc-8f1f-16fda89fcf85}">
		<property name="name">
			<value>SKIP</value>
		</property>
		<relationship name="folder">
			<destination>{07d4a1d2-ef61-47f4-a9c3-24291ec9a57a}</destination>
		</relationship>
		<relationship name="parameter">
			<destination>{8be75758-a79e-4f14-8291-900f5134fc38}</destination>
		</relationship>
	</object>
	<object class="GameParameter" id="{8be75758-a79e-4f14-8291-900f5134fc38}">
		<property name="parameterType">
			<value>1</value>
		</property>
		<property name="maximum">
			<value>2</value>
		</property>
		<property name="initialValue">
			<value>1</value>
		</property>
	</object>
</objects>
